arequest/__init__.py
arequest/auth.py
arequest/client.py
arequest/parser.py
arequest-1.2.0.dist-info/licenses/LICENSE
arequest-1.2.0.dist-info/METADATA
arequest-1.2.0.dist-info/WHEEL
arequest-1.2.0.dist-info/top_level.txt
arequest-1.2.0.dist-info/RECORD
