Metadata-Version: 2.4
Name: arequest
Version: 1.2.0
Summary: Ultra-fast async HTTP client for web scraping - faster than aiohttp with requests-like API
Author-email: Abhra <abhraayan@gmail.com>
Maintainer-email: Abhra <abhraayan@gmail.com>
License-Expression: MIT
Project-URL: Homepage, https://github.com/abhrajyoti-01/arequest
Project-URL: Repository, https://github.com/abhrajyoti-01/arequest
Project-URL: Issues, https://github.com/abhrajyoti-01/arequest/issues
Keywords: async,http,client,requests,asyncio,aiohttp,fast,performance
Classifier: Development Status :: 4 - Beta
Classifier: Intended Audience :: Developers
Classifier: Programming Language :: Python :: 3
Classifier: Programming Language :: Python :: 3.9
Classifier: Programming Language :: Python :: 3.10
Classifier: Programming Language :: Python :: 3.11
Classifier: Programming Language :: Python :: 3.12
Classifier: Programming Language :: Python :: 3.13
Classifier: Topic :: Internet :: WWW/HTTP
Classifier: Topic :: Software Development :: Libraries :: Python Modules
Classifier: Framework :: AsyncIO
Requires-Python: >=3.9
License-File: LICENSE
Requires-Dist: httptools>=0.6.0
Requires-Dist: orjson>=3.8.0
Provides-Extra: uvloop
Requires-Dist: uvloop>=0.17.0; platform_system != "Windows" and extra == "uvloop"
Provides-Extra: dev
Requires-Dist: pytest>=7.0.0; extra == "dev"
Requires-Dist: pytest-asyncio>=0.21.0; extra == "dev"
Requires-Dist: aiohttp>=3.8.0; extra == "dev"
Requires-Dist: ruff>=0.1.0; extra == "dev"
Provides-Extra: all
Requires-Dist: uvloop>=0.17.0; platform_system != "Windows" and extra == "all"
Dynamic: license-file
